{
	"configurations" : 
	[
		{
			"directories" : 
			[
				{
					"build" : ".",
					"jsonFile" : "directory-.-Debug-f5ebdc15457944623624.json",
					"minimumCMakeVersion" : 
					{
						"string" : "3.23"
					},
					"projectIndex" : 0,
					"source" : ".",
					"targetIndexes" : 
					[
						0
					]
				}
			],
			"name" : "Debug",
			"projects" : 
			[
				{
					"directoryIndexes" : 
					[
						0
					],
					"name" : "discount_calculator",
					"targetIndexes" : 
					[
						0
					]
				}
			],
			"targets" : 
			[
				{
					"directoryIndex" : 0,
					"id" : "discount_calculator::@6890427a1f51a3e7e1df",
					"jsonFile" : "target-discount_calculator-Debug-430aa3aa044e98a3b536.json",
					"name" : "discount_calculator",
					"projectIndex" : 0
				}
			]
		}
	],
	"kind" : "codemodel",
	"paths" : 
	{
		"build" : "/Users/nadundhananjaya/CLionProjects/discount_calculator/cmake-build-debug",
		"source" : "/Users/nadundhananjaya/CLionProjects/discount_calculator"
	},
	"version" : 
	{
		"major" : 2,
		"minor" : 4
	}
}
